less2sass/less2sass.py
less2sass/cli.py
less2sass/__init__.py
less2sass-0.1.0.dist-info/DESCRIPTION.rst
less2sass-0.1.0.dist-info/WHEEL
less2sass-0.1.0.dist-info/metadata.json
less2sass-0.1.0.dist-info/entry_points.txt
less2sass-0.1.0.dist-info/METADATA
less2sass-0.1.0.dist-info/RECORD
less2sass-0.1.0.dist-info/top_level.txt
