Metadata-Version: 2.0
Name: less2sass
Version: 0.1.0
Summary: Python package that will convert valid less code into sass code.
Home-page: https://github.com/sydhenry/less2sass
Author: Sydney Henry
Author-email: shenry@handycodejob.com
License: ISCL
Keywords: less2sass
Platform: UNKNOWN
Classifier: Development Status :: 2 - Pre-Alpha
Classifier: Intended Audience :: Developers
Classifier: License :: OSI Approved :: ISC License (ISCL)
Classifier: Natural Language :: English
Classifier: Programming Language :: Python :: 2
Classifier: Programming Language :: Python :: 2.6
Classifier: Programming Language :: Python :: 2.7
Classifier: Programming Language :: Python :: 3
Classifier: Programming Language :: Python :: 3.3
Classifier: Programming Language :: Python :: 3.4
Requires-Dist: click (<5.0)
